armilla_watsonx/Armilla_AI.py
armilla_watsonx/__init__.py
armilla_watsonx-0.0.1.dist-info/LICENSE
armilla_watsonx-0.0.1.dist-info/METADATA
armilla_watsonx-0.0.1.dist-info/WHEEL
armilla_watsonx-0.0.1.dist-info/top_level.txt
armilla_watsonx-0.0.1.dist-info/RECORD
