Metadata-Version: 2.1
Name: armilla_watsonx
Version: 0.0.1
Summary: Integration between Watsonx.ai and Armilla AI
Author-email: Rainbow Li <rainbow@armilla.ai>
Project-URL: Homepage, https://github.com/pypa/sampleproject
Project-URL: Issues, https://github.com/pypa/sampleproject/issues
Classifier: Programming Language :: Python :: 3
Classifier: License :: OSI Approved :: MIT License
Classifier: Operating System :: OS Independent
Requires-Python: >=3.8
License-File: LICENSE
